CHANGELOG.md
LICENSE
MANIFEST.in
README.md
setup.cfg
setup.py
par/__init__.py
par/_compat.py
par/bootstrap_ext.py
par/gwiki.py
par/md.py
par/pyPEG.py
par/semantic_ext.py
par/setup.py
par.egg-info/PKG-INFO
par.egg-info/SOURCES.txt
par.egg-info/dependency_links.txt
par.egg-info/not-zip-safe
par.egg-info/top_level.txt
test/test_md.py