Metadata-Version: 1.1
Name: par
Version: 1.3.2
Summary: A simple structured text parser project
Home-page: https://github.com/limodou/par
Author: limodou
Author-email: limodou@gmail.com
License: BSD
Keywords: parser peg
Platform: any
Classifier: Development Status :: 2 - Pre-Alpha
Classifier: Intended Audience :: Developers
Classifier: License :: OSI Approved :: BSD License
Classifier: Programming Language :: Python
Classifier: Operating System :: OS Independent
Classifier: Programming Language :: Python :: 2.6
Classifier: Programming Language :: Python :: 2.7
Classifier: Programming Language :: Python :: 3.3
Classifier: Programming Language :: Python :: 3.4
